split_previous/__init__.py
plover_cycle_homophones-0.0.2.dist-info/METADATA
plover_cycle_homophones-0.0.2.dist-info/WHEEL
plover_cycle_homophones-0.0.2.dist-info/entry_points.txt
plover_cycle_homophones-0.0.2.dist-info/top_level.txt
plover_cycle_homophones-0.0.2.dist-info/zip-safe
plover_cycle_homophones-0.0.2.dist-info/RECORD
