Metadata-Version: 2.1
Name: plover-cycle-homophones
Version: 0.0.2
Summary: =?utf-8?q?Companion_plugin_for_B=C3=A9poSt=C3=A9no_-_cycle_through_homophones_and_split_words_at_previous_stroke?=
Home-page: https://github.com/AntoineBalaine/plover_cycle_homophones
Author: AntoineBalaine
License: MIT
Keywords: =?utf-8?q?plover=5Fplugin_plover_b=C3=A9po_steno?=
Requires-Dist: plover (>=4.0.0.dev6)
